KratosMultiphysics/.libs/KratosHDF5Application.pyd
KratosMultiphysics/.libs/KratosHDF5Core.dll
KratosMultiphysics/.libs/KratosHDF5Core.lib
KratosMultiphysics/HDF5Application/__init__.py
KratosMultiphysics/HDF5Application/create_xdmf_file.py
KratosMultiphysics/HDF5Application/import_model_part_from_hdf5_process.py
KratosMultiphysics/HDF5Application/initialization_from_hdf5_process.py
KratosMultiphysics/HDF5Application/line_output_process.py
KratosMultiphysics/HDF5Application/multiple_mesh_temporal_output_process.py
KratosMultiphysics/HDF5Application/point_set_output_process.py
KratosMultiphysics/HDF5Application/single_mesh_primal_output_process.py
KratosMultiphysics/HDF5Application/single_mesh_temporal_input_process.py
KratosMultiphysics/HDF5Application/single_mesh_temporal_output_process.py
KratosMultiphysics/HDF5Application/single_mesh_xdmf_output_process.py
KratosMultiphysics/HDF5Application/user_defined_io_process.py
KratosMultiphysics/HDF5Application/utils.py
KratosMultiphysics/HDF5Application/xdmf_utils.py
KratosMultiphysics/HDF5Application/core/__init__.py
KratosMultiphysics/HDF5Application/core/controllers.py
KratosMultiphysics/HDF5Application/core/file_io.py
KratosMultiphysics/HDF5Application/core/processes.py
KratosMultiphysics/HDF5Application/core/utils.py
KratosMultiphysics/HDF5Application/core/xdmf.py
KratosMultiphysics/HDF5Application/core/operations/__init__.py
KratosMultiphysics/HDF5Application/core/operations/model_part.py
KratosMultiphysics/HDF5Application/core/operations/system.py
KratosMultiphysics/HDF5Application/core/operations/xdmf.py
KratosHDF5Application-10.2.1.dist-info/METADATA
KratosHDF5Application-10.2.1.dist-info/WHEEL
KratosHDF5Application-10.2.1.dist-info/top_level.txt
KratosHDF5Application-10.2.1.dist-info/RECORD
